usesend/__init__.py
usesend/campaigns.py
usesend/contacts.py
usesend/domains.py
usesend/emails.py
usesend/py.typed
usesend/types.py
usesend/usesend.py
usesend-0.2.8.dist-info/LICENSE
usesend-0.2.8.dist-info/METADATA
usesend-0.2.8.dist-info/WHEEL
usesend-0.2.8.dist-info/RECORD
