Metadata-Version: 2.1
Name: usesend
Version: 0.2.8
Summary: Python SDK for the UseSend API
License: MIT
Author: UseSend
Requires-Python: >=3.8,<4.0
Classifier: License :: OSI Approved :: MIT License
Classifier: Programming Language :: Python :: 3
Classifier: Programming Language :: Python :: 3.8
Classifier: Programming Language :: Python :: 3.9
Classifier: Programming Language :: Python :: 3.10
Classifier: Programming Language :: Python :: 3.11
Classifier: Programming Language :: Python :: 3.12
Requires-Dist: requests (>=2.32.0,<3.0.0)
Requires-Dist: typing_extensions (>=4.7)
